yuvi/__init__.py
yuvi/downloader_utils.py
yuvi/drive.py
yuvi/languages.py
yuvi/main.py
yuvi/multipart_downloader.py
yuvi/assets/Kemono.ico
yuvi/assets/Kemono.png
yuvi/assets/discord.png
yuvi/assets/github.png
yuvi/assets/instagram.png
yuvi_downloader-5.0.1.dist-info/METADATA
yuvi_downloader-5.0.1.dist-info/WHEEL
yuvi_downloader-5.0.1.dist-info/entry_points.txt
yuvi_downloader-5.0.1.dist-info/top_level.txt
yuvi_downloader-5.0.1.dist-info/RECORD
