Metadata-Version: 2.4
Name: yuvi-downloader
Version: 5.0.1
Summary: A downloader application for Kemono and Coomer sites.
Home-page: https://github.com/Yuvi9587/Kemono-Downloader-Public
Author: Yuvi
Author-email: your_email@example.com
Classifier: Development Status :: 4 - Beta
Classifier: Intended Audience :: End Users/Desktop
Classifier: License :: OSI Approved :: MIT License
Classifier: Programming Language :: Python :: 3
Classifier: Programming Language :: Python :: 3.8
Classifier: Programming Language :: Python :: 3.9
Classifier: Programming Language :: Python :: 3.10
Classifier: Programming Language :: Python :: 3.11
Classifier: Operating System :: OS Independent
Classifier: Topic :: Internet :: WWW/HTTP
Classifier: Topic :: Utilities
Classifier: Environment :: X11 Applications :: Qt
Requires-Python: >=3.8
Requires-Dist: PyQt5>=5.15
Requires-Dist: requests>=2.20
Requires-Dist: Pillow>=8.0
Requires-Dist: mega.py>=1.0.8
Requires-Dist: gdown>=4.0.0
Requires-Dist: setuptools
Dynamic: author
Dynamic: author-email
Dynamic: classifier
Dynamic: description
Dynamic: description-content-type
Dynamic: home-page
Dynamic: requires-dist
Dynamic: requires-python
Dynamic: summary
